README.rst
djsnowpack.py
setup.py
djsnowpack.egg-info/PKG-INFO
djsnowpack.egg-info/SOURCES.txt
djsnowpack.egg-info/dependency_links.txt
djsnowpack.egg-info/requires.txt
djsnowpack.egg-info/top_level.txt
djsnowpack_example/__init__.py
djsnowpack_example/manage.py
djsnowpack_example/settings.py
djsnowpack_example/urls.py
djsnowpack_example/wsgi.py