Metadata-Version: 2.1
Name: djsnowpack
Version: 0.1.3
Summary: Django + Snowpack = djsnowpack
Home-page: https://yourlabs.io/oss/djsnowpack
Author: James Pic
Author-email: jamespic@gmail.com
License: MIT
Keywords: django cli
Platform: UNKNOWN
Requires-Python: >=3
Provides-Extra: test
